{"version": "1", "message": "ERROR: Hidden Testcases server unreachable.", "problem_id": "ads1_m14_a2", "user_id": "pranay0124@msitprogram.net", "score": {"sample": {"0": {"execution_time": 0.2136368751525879, "passed": true}, "1": {"execution_time": 0.18203282356262207, "passed": true}, "2": {"execution_time": 0.18752193450927734, "passed": true}, "3": {"execution_time": 0.18855667114257812, "passed": true}, "4": {"execution_time": 0.1835179328918457, "passed": true}, "5": {"execution_time": 0.18300890922546387, "passed": true}}}, "check_style_score": "0/1"}